Multifunctional_Calculator/NumbersCalculator.py
Multifunctional_Calculator/StringsCalculator.py
Multifunctional_Calculator/__init__.py
multifunctional_calculator-0.0.5.dist-info/licenses/LICENSE
multifunctional_calculator-0.0.5.dist-info/METADATA
multifunctional_calculator-0.0.5.dist-info/WHEEL
multifunctional_calculator-0.0.5.dist-info/top_level.txt
multifunctional_calculator-0.0.5.dist-info/RECORD
