Metadata-Version: 2.4
Name: Multifunctional-Calculator
Version: 0.0.5
Summary: 多功能计算库（整合decimal）
Author-email: Linsc <1344343923@qq.com>
Classifier: Programming Language :: Python :: 3
Classifier: License :: OSI Approved :: MIT License
Classifier: Operating System :: OS Independent
Requires-Python: >=3.10
License-File: LICENSE
Dynamic: license-file
